stringcalc/__init__.py
stringcalc/_version.py
stringcalc/cli.py
stringcalc/frets.py
stringcalc/py.typed
stringcalc/tension.py
stringcalc/data/__init__.py
stringcalc/data/aquila-nng.csv
stringcalc/data/daddario-stp.csv
stringcalc/data/daddario-tension.csv
stringcalc/data/ghs.csv
stringcalc/data/stringjoy.csv
stringcalc/data/worth.csv
stringcalc-0.1.0.dist-info/METADATA
stringcalc-0.1.0.dist-info/WHEEL
stringcalc-0.1.0.dist-info/entry_points.txt
stringcalc-0.1.0.dist-info/licenses/LICENSE
stringcalc-0.1.0.dist-info/RECORD
