Metadata-Version: 2.4
Name: stringcalc
Version: 0.1.0
Summary: Instrument string calculations
Project-URL: Home, https://github.com/zmoon/stringcalc
Project-URL: Source, https://github.com/zmoon/stringcalc
Project-URL: Documentation, https://stringcalc.readthedocs.io
Author-email: zmoon <zmoon92@gmail.com>
License-Expression: MIT
License-File: LICENSE
Classifier: License :: OSI Approved :: MIT License
Requires-Python: <4,>=3.10
Requires-Dist: numpy>=1.21
Requires-Dist: pandas
Requires-Dist: pint>=0.22
Requires-Dist: pyabc2
Provides-Extra: cli
Requires-Dist: rich; extra == 'cli'
Requires-Dist: typer; extra == 'cli'
